zero_log_parser/__init__.py
zero_log_parser/__main__.py
zero_log_parser/cli.py
zero_log_parser/core.py
zero_log_parser/plot_cli.py
zero_log_parser/plotting.py
zero_log_parser/py.typed
zero_log_parser/utils.py
zero_log_parser-2.2.0.dist-info/METADATA
zero_log_parser-2.2.0.dist-info/WHEEL
zero_log_parser-2.2.0.dist-info/entry_points.txt
zero_log_parser-2.2.0.dist-info/top_level.txt
zero_log_parser-2.2.0.dist-info/RECORD
