Metadata-Version: 2.4
Name: zero-log-parser
Version: 2.2.0
Summary: A modern parser for Zero Motorcycle log files with structured data extraction
Author: Kim Burgess, Keith Thomas
Author-email: Ilja Radusch <ilja@radusch.com>, "Brian T. Rice" <briantrice@gmail.com>
Maintainer-email: Ilja Radusch <ilja@radusch.com>
License: MIT
Project-URL: Homepage, https://github.com/ilja-radusch/zero-log-parser
Project-URL: Repository, https://github.com/ilja-radusch/zero-log-parser
Project-URL: Issues, https://github.com/ilja-radusch/zero-log-parser/issues
Project-URL: Documentation, https://github.com/ilja-radusch/zero-log-parser/blob/main/README.md
Keywords: zero,motorcycle,log,parser,mbb,bms,battery
Classifier: Development Status :: 4 - Beta
Classifier: Intended Audience :: End Users/Desktop
Classifier: Intended Audience :: Developers
Classifier: License :: OSI Approved :: MIT License
Classifier: Operating System :: OS Independent
Classifier: Programming Language :: Python :: 3
Classifier: Programming Language :: Python :: 3.10
Classifier: Programming Language :: Python :: 3.11
Classifier: Programming Language :: Python :: 3.12
Classifier: Topic :: System :: Hardware
Classifier: Topic :: Utilities
Requires-Python: >=3.10
Provides-Extra: plotting
Requires-Dist: plotly>=5.0; extra == "plotting"
Requires-Dist: pandas>=1.5.0; extra == "plotting"
Provides-Extra: dev
Requires-Dist: pytest>=7.0; extra == "dev"
Requires-Dist: pytest-cov>=4.0; extra == "dev"
Requires-Dist: black>=23.0; extra == "dev"
Requires-Dist: ruff>=0.1.0; extra == "dev"
Requires-Dist: mypy>=1.0; extra == "dev"
Requires-Dist: plotly>=5.0; extra == "dev"
Requires-Dist: pandas>=1.5.0; extra == "dev"
Provides-Extra: test
Requires-Dist: pytest>=7.0; extra == "test"
Requires-Dist: pytest-cov>=4.0; extra == "test"
